{"_path":"/docs/api/commands/module","_dir":"commands","_draft":false,"_partial":false,"_locale":"","title":"nuxi module","description":"Search and add modules to your Nuxt application with the command line.","links":[{"label":"Source","icon":"i-simple-icons-github","to":"https://github.com/nuxt/cli/blob/main/src/commands/module/","size":"xs"}],"body":{"type":"root","children":[{"type":"element","tag":"p","props":{},"children":[{"type":"text","value":"Nuxi provides a few utilities to work with "},{"type":"element","tag":"a","props":{"href":"/modules"},"children":[{"type":"text","value":"Nuxt modules"}]},{"type":"text","value":" seamlessly."}]},{"type":"element","tag":"h2","props":{"id":"nuxi-module-add"},"children":[{"type":"text","value":"nuxi module add"}]},{"type":"element","tag":"pre","props":{"className":"language-bash shiki shiki-themes material-theme-lighter material-theme-lighter material-theme-palenight","code":"npx nuxi module add <NAME>\n","filename":"Terminal","language":"bash","meta":"","style":""},"children":[{"type":"element","tag":"code","props":{"__ignoreMap":""},"children":[{"type":"element","tag":"span","props":{"class":"line","line":1},"children":[{"type":"element","tag":"span","props":{"style":"--shiki-light:#E2931D;--shiki-default:#E2931D;--shiki-dark:#FFCB6B"},"children":[{"type":"text","value":"npx"}]},{"type":"element","tag":"span","props":{"style":"--shiki-light:#91B859;--shiki-default:#91B859;--shiki-dark:#C3E88D"},"children":[{"type":"text","value":" nuxi"}]},{"type":"element","tag":"span","props":{"style":"--shiki-light:#91B859;--shiki-default:#91B859;--shiki-dark:#C3E88D"},"children":[{"type":"text","value":" module"}]},{"type":"element","tag":"span","props":{"style":"--shiki-light:#91B859;--shiki-default:#91B859;--shiki-dark:#C3E88D"},"children":[{"type":"text","value":" add"}]},{"type":"element","tag":"span","props":{"style":"--shiki-light:#39ADB5;--shiki-default:#39ADB5;--shiki-dark:#89DDFF"},"children":[{"type":"text","value":" <"}]},{"type":"element","tag":"span","props":{"style":"--shiki-light:#91B859;--shiki-default:#91B859;--shiki-dark:#C3E88D"},"children":[{"type":"text","value":"NAM"}]},{"type":"element","tag":"span","props":{"style":"--shiki-light:#90A4AE;--shiki-default:#90A4AE;--shiki-dark:#BABED8"},"children":[{"type":"text","value":"E"}]},{"type":"element","tag":"span","props":{"style":"--shiki-light:#39ADB5;--shiki-default:#39ADB5;--shiki-dark:#89DDFF"},"children":[{"type":"text","value":">\n"}]}]}]}]},{"type":"text","value":"\n\n\n\n\n\n\n\n\n\n\n\n\n\n\n\n"},{"type":"element","tag":"table","props":{},"children":[{"type":"element","tag":"thead","props":{},"children":[{"type":"element","tag":"tr","props":{},"children":[{"type":"element","tag":"th","props":{},"children":[{"type":"text","value":"Option"}]},{"type":"element","tag":"th","props":{},"children":[{"type":"text","value":"Default"}]},{"type":"element","tag":"th","props":{},"children":[{"type":"text","value":"Description"}]}]}]},{"type":"element","tag":"tbody","props":{},"children":[{"type":"element","tag":"tr","props":{},"children":[{"type":"element","tag":"td","props":{},"children":[{"type":"element","tag":"code","props":{"className":[]},"children":[{"type":"text","value":"NAME"}]}]},{"type":"element","tag":"td","props":{},"children":[{"type":"text","value":"-"}]},{"type":"element","tag":"td","props":{},"children":[{"type":"text","value":"The name of the module to install."}]}]}]}]},{"type":"element","tag":"p","props":{},"children":[{"type":"text","value":"The command lets you install "},{"type":"element","tag":"a","props":{"href":"/modules"},"children":[{"type":"text","value":"Nuxt modules"}]},{"type":"text","value":" in your application with no manual work."}]},{"type":"element","tag":"p","props":{},"children":[{"type":"text","value":"When running the command, it will:"}]},{"type":"element","tag":"ul","props":{},"children":[{"type":"element","tag":"li","props":{},"children":[{"type":"text","value":"install the module as a dependency using your package manager"}]},{"type":"element","tag":"li","props":{},"children":[{"type":"text","value":"add it to your "},{"type":"element","tag":"a","props":{"href":"/docs/guide/directory-structure/package"},"children":[{"type":"text","value":"package.json"}]},{"type":"text","value":" file"}]},{"type":"element","tag":"li","props":{},"children":[{"type":"text","value":"update your "},{"type":"element","tag":"a","props":{"href":"/docs/guide/directory-structure/nuxt-config"},"children":[{"type":"element","tag":"code","props":{"className":[]},"children":[{"type":"text","value":"nuxt.config"}]}]},{"type":"text","value":" file"}]}]},{"type":"element","tag":"p","props":{},"children":[{"type":"element","tag":"strong","props":{},"children":[{"type":"text","value":"Example:"}]}]},{"type":"element","tag":"p","props":{},"children":[{"type":"text","value":"Installing the "},{"type":"element","tag":"a","props":{"href":"/modules/pinia"},"children":[{"type":"element","tag":"code","props":{"className":[]},"children":[{"type":"text","value":"Pinia"}]}]},{"type":"text","value":" module"}]},{"type":"element","tag":"pre","props":{"className":"language-bash shiki shiki-themes material-theme-lighter material-theme-lighter material-theme-palenight","code":"npx nuxi module add pinia \n","filename":"Terminal","language":"bash","meta":"","style":""},"children":[{"type":"element","tag":"code","props":{"__ignoreMap":""},"children":[{"type":"element","tag":"span","props":{"class":"line","line":1},"children":[{"type":"element","tag":"span","props":{"style":"--shiki-light:#E2931D;--shiki-default:#E2931D;--shiki-dark:#FFCB6B"},"children":[{"type":"text","value":"npx"}]},{"type":"element","tag":"span","props":{"style":"--shiki-light:#91B859;--shiki-default:#91B859;--shiki-dark:#C3E88D"},"children":[{"type":"text","value":" nuxi"}]},{"type":"element","tag":"span","props":{"style":"--shiki-light:#91B859;--shiki-default:#91B859;--shiki-dark:#C3E88D"},"children":[{"type":"text","value":" module"}]},{"type":"element","tag":"span","props":{"style":"--shiki-light:#91B859;--shiki-default:#91B859;--shiki-dark:#C3E88D"},"children":[{"type":"text","value":" add"}]},{"type":"element","tag":"span","props":{"style":"--shiki-light:#91B859;--shiki-default:#91B859;--shiki-dark:#C3E88D"},"children":[{"type":"text","value":" pinia\n"}]}]}]}]},{"type":"element","tag":"h2","props":{"id":"nuxi-module-search"},"children":[{"type":"text","value":"nuxi module search"}]},{"type":"element","tag":"pre","props":{"className":"language-bash shiki shiki-themes material-theme-lighter material-theme-lighter material-theme-palenight","code":"npx nuxi module search <QUERY>\n","filename":"Terminal","language":"bash","meta":"","style":""},"children":[{"type":"element","tag":"code","props":{"__ignoreMap":""},"children":[{"type":"element","tag":"span","props":{"class":"line","line":1},"children":[{"type":"element","tag":"span","props":{"style":"--shiki-light:#E2931D;--shiki-default:#E2931D;--shiki-dark:#FFCB6B"},"children":[{"type":"text","value":"npx"}]},{"type":"element","tag":"span","props":{"style":"--shiki-light:#91B859;--shiki-default:#91B859;--shiki-dark:#C3E88D"},"children":[{"type":"text","value":" nuxi"}]},{"type":"element","tag":"span","props":{"style":"--shiki-light:#91B859;--shiki-default:#91B859;--shiki-dark:#C3E88D"},"children":[{"type":"text","value":" module"}]},{"type":"element","tag":"span","props":{"style":"--shiki-light:#91B859;--shiki-default:#91B859;--shiki-dark:#C3E88D"},"children":[{"type":"text","value":" search"}]},{"type":"element","tag":"span","props":{"style":"--shiki-light:#39ADB5;--shiki-default:#39ADB5;--shiki-dark:#89DDFF"},"children":[{"type":"text","value":" <"}]},{"type":"element","tag":"span","props":{"style":"--shiki-light:#91B859;--shiki-default:#91B859;--shiki-dark:#C3E88D"},"children":[{"type":"text","value":"QUER"}]},{"type":"element","tag":"span","props":{"style":"--shiki-light:#90A4AE;--shiki-default:#90A4AE;--shiki-dark:#BABED8"},"children":[{"type":"text","value":"Y"}]},{"type":"element","tag":"span","props":{"style":"--shiki-light:#39ADB5;--shiki-default:#39ADB5;--shiki-dark:#89DDFF"},"children":[{"type":"text","value":">\n"}]}]}]}]},{"type":"text","value":"\n\n\n\n\n\n\n\n\n\n\n\n\n\n\n\n"},{"type":"element","tag":"table","props":{},"children":[{"type":"element","tag":"thead","props":{},"children":[{"type":"element","tag":"tr","props":{},"children":[{"type":"element","tag":"th","props":{},"children":[{"type":"text","value":"Option"}]},{"type":"element","tag":"th","props":{},"children":[{"type":"text","value":"Default"}]},{"type":"element","tag":"th","props":{},"children":[{"type":"text","value":"Description"}]}]}]},{"type":"element","tag":"tbody","props":{},"children":[{"type":"element","tag":"tr","props":{},"children":[{"type":"element","tag":"td","props":{},"children":[{"type":"element","tag":"code","props":{"className":[]},"children":[{"type":"text","value":"QUERY"}]}]},{"type":"element","tag":"td","props":{},"children":[{"type":"text","value":"-"}]},{"type":"element","tag":"td","props":{},"children":[{"type":"text","value":"The name of the module to search for."}]}]}]}]},{"type":"element","tag":"p","props":{},"children":[{"type":"text","value":"The command searches for Nuxt modules matching your query that are compatible with your Nuxt version."}]},{"type":"element","tag":"p","props":{},"children":[{"type":"element","tag":"strong","props":{},"children":[{"type":"text","value":"Example:"}]}]},{"type":"element","tag":"pre","props":{"className":"language-bash shiki shiki-themes material-theme-lighter material-theme-lighter material-theme-palenight","code":"npx nuxi module search pinia\n","filename":"Terminal","language":"bash","meta":"","style":""},"children":[{"type":"element","tag":"code","props":{"__ignoreMap":""},"children":[{"type":"element","tag":"span","props":{"class":"line","line":1},"children":[{"type":"element","tag":"span","props":{"style":"--shiki-light:#E2931D;--shiki-default:#E2931D;--shiki-dark:#FFCB6B"},"children":[{"type":"text","value":"npx"}]},{"type":"element","tag":"span","props":{"style":"--shiki-light:#91B859;--shiki-default:#91B859;--shiki-dark:#C3E88D"},"children":[{"type":"text","value":" nuxi"}]},{"type":"element","tag":"span","props":{"style":"--shiki-light:#91B859;--shiki-default:#91B859;--shiki-dark:#C3E88D"},"children":[{"type":"text","value":" module"}]},{"type":"element","tag":"span","props":{"style":"--shiki-light:#91B859;--shiki-default:#91B859;--shiki-dark:#C3E88D"},"children":[{"type":"text","value":" search"}]},{"type":"element","tag":"span","props":{"style":"--shiki-light:#91B859;--shiki-default:#91B859;--shiki-dark:#C3E88D"},"children":[{"type":"text","value":" pinia\n"}]}]}]}]},{"type":"element","tag":"style","props":{},"children":[{"type":"text","value":"html .light .shiki span {color: var(--shiki-light);background: var(--shiki-light-bg);font-style: var(--shiki-light-font-style);font-weight: var(--shiki-light-font-weight);text-decoration: var(--shiki-light-text-decoration);}html.light .shiki span {color: var(--shiki-light);background: var(--shiki-light-bg);font-style: var(--shiki-light-font-style);font-weight: var(--shiki-light-font-weight);text-decoration: var(--shiki-light-text-decoration);}html .default .shiki span {color: var(--shiki-default);background: var(--shiki-default-bg);font-style: var(--shiki-default-font-style);font-weight: var(--shiki-default-font-weight);text-decoration: var(--shiki-default-text-decoration);}html .shiki span {color: var(--shiki-default);background: var(--shiki-default-bg);font-style: var(--shiki-default-font-style);font-weight: var(--shiki-default-font-weight);text-decoration: var(--shiki-default-text-decoration);}html .dark .shiki span {color: var(--shiki-dark);background: var(--shiki-dark-bg);font-style: var(--shiki-dark-font-style);font-weight: var(--shiki-dark-font-weight);text-decoration: var(--shiki-dark-text-decoration);}html.dark .shiki span {color: var(--shiki-dark);background: var(--shiki-dark-bg);font-style: var(--shiki-dark-font-style);font-weight: var(--shiki-dark-font-weight);text-decoration: var(--shiki-dark-text-decoration);}"}]}],"toc":{"title":"","searchDepth":2,"depth":2,"links":[{"id":"nuxi-module-add","depth":2,"text":"nuxi module add"},{"id":"nuxi-module-search","depth":2,"text":"nuxi module search"}]}},"_type":"markdown","_id":"nuxt-docs:1.docs:3.api:4.commands:module.md","_source":"nuxt-docs","_file":"1.docs/3.api/4.commands/module.md","_extension":"md"}