{"_path":"/docs/bridge/bridge-composition-api","_dir":"bridge","_draft":false,"_partial":false,"_locale":"","title":"Legacy Composition API","description":"Learn how to migrate to Composition API with Nuxt Bridge.","body":{"type":"root","children":[{"type":"element","tag":"p","props":{},"children":[{"type":"text","value":"Nuxt Bridge provides access to Composition API syntax. It is specifically designed to be aligned with Nuxt 3. Because of this, there are a few extra steps to take when enabling Nuxt Bridge, if you have been using the Composition API previously."}]},{"type":"element","tag":"h2","props":{"id":"remove-modules"},"children":[{"type":"text","value":"Remove Modules"}]},{"type":"element","tag":"ul","props":{},"children":[{"type":"element","tag":"li","props":{},"children":[{"type":"text","value":"Remove "},{"type":"element","tag":"code","props":{"className":[]},"children":[{"type":"text","value":"@vue/composition-api"}]},{"type":"text","value":" from your dependencies."}]},{"type":"element","tag":"li","props":{},"children":[{"type":"text","value":"Remove "},{"type":"element","tag":"code","props":{"className":[]},"children":[{"type":"text","value":"@nuxtjs/composition-api"}]},{"type":"text","value":" from your dependencies (and from your modules in "},{"type":"element","tag":"code","props":{"className":[]},"children":[{"type":"text","value":"nuxt.config"}]},{"type":"text","value":")."}]}]},{"type":"element","tag":"h2","props":{"id":"using-vuecomposition-api"},"children":[{"type":"text","value":"Using "},{"type":"element","tag":"code","props":{"className":[]},"children":[{"type":"text","value":"@vue/composition-api"}]}]},{"type":"element","tag":"p","props":{},"children":[{"type":"text","value":"If you have been using just "},{"type":"element","tag":"code","props":{"className":[]},"children":[{"type":"text","value":"@vue/composition-api"}]},{"type":"text","value":" and not "},{"type":"element","tag":"code","props":{"className":[]},"children":[{"type":"text","value":"@nuxtjs/composition-api"}]},{"type":"text","value":", then things are very straightforward."}]},{"type":"element","tag":"ol","props":{},"children":[{"type":"element","tag":"li","props":{},"children":[{"type":"text","value":"First, remove the plugin where you are manually registering the Composition API. Nuxt Bridge will handle this for you."},{"type":"element","tag":"pre","props":{"className":"language-diff shiki shiki-themes material-theme-lighter material-theme-lighter material-theme-palenight","code":"- import Vue from 'vue'\n- import VueCompositionApi from '@vue/composition-api'\n-\n- Vue.use(VueCompositionApi)\n","language":"diff","meta":"","style":""},"children":[{"type":"element","tag":"code","props":{"__ignoreMap":""},"children":[{"type":"element","tag":"span","props":{"class":"line","line":1},"children":[{"type":"element","tag":"span","props":{"style":"--shiki-light:#39ADB5;--shiki-default:#39ADB5;--shiki-dark:#89DDFF"},"children":[{"type":"text","value":"-"}]},{"type":"element","tag":"span","props":{"style":"--shiki-light:#E53935;--shiki-default:#E53935;--shiki-dark:#F07178"},"children":[{"type":"text","value":" import Vue from 'vue'\n"}]}]},{"type":"element","tag":"span","props":{"class":"line","line":2},"children":[{"type":"element","tag":"span","props":{"style":"--shiki-light:#39ADB5;--shiki-default:#39ADB5;--shiki-dark:#89DDFF"},"children":[{"type":"text","value":"-"}]},{"type":"element","tag":"span","props":{"style":"--shiki-light:#E53935;--shiki-default:#E53935;--shiki-dark:#F07178"},"children":[{"type":"text","value":" import VueCompositionApi from '@vue/composition-api'\n"}]}]},{"type":"element","tag":"span","props":{"class":"line","line":3},"children":[{"type":"element","tag":"span","props":{"style":"--shiki-light:#39ADB5;--shiki-default:#39ADB5;--shiki-dark:#89DDFF"},"children":[{"type":"text","value":"-\n"}]}]},{"type":"element","tag":"span","props":{"class":"line","line":4},"children":[{"type":"element","tag":"span","props":{"style":"--shiki-light:#39ADB5;--shiki-default:#39ADB5;--shiki-dark:#89DDFF"},"children":[{"type":"text","value":"-"}]},{"type":"element","tag":"span","props":{"style":"--shiki-light:#E53935;--shiki-default:#E53935;--shiki-dark:#F07178"},"children":[{"type":"text","value":" Vue.use(VueCompositionApi)\n"}]}]}]}]}]},{"type":"element","tag":"li","props":{},"children":[{"type":"text","value":"Otherwise, there is nothing you need to do. However, if you want, you can remove your explicit imports from "},{"type":"element","tag":"code","props":{"className":[]},"children":[{"type":"text","value":"@vue/composition-api"}]},{"type":"text","value":" and rely on Nuxt Bridge auto-importing them for you."}]}]},{"type":"element","tag":"h2","props":{"id":"migrating-from-nuxtjscomposition-api"},"children":[{"type":"text","value":"Migrating from "},{"type":"element","tag":"code","props":{"className":[]},"children":[{"type":"text","value":"@nuxtjs/composition-api"}]}]},{"type":"element","tag":"p","props":{},"children":[{"type":"text","value":"Nuxt Bridge implements the Composition API slightly differently from "},{"type":"element","tag":"code","props":{"className":[]},"children":[{"type":"text","value":"@nuxtjs/composition-api"}]},{"type":"text","value":" and provides different composables (designed to be aligned with the composables that Nuxt 3 provides)."}]},{"type":"element","tag":"p","props":{},"children":[{"type":"text","value":"Because some composables have been removed and don't yet have a replacement, this will be a slightly more complicated process."}]},{"type":"element","tag":"h3","props":{"id":"remove-nuxtjscomposition-apimodule-from-your-buildmodules"},"children":[{"type":"text","value":"Remove "},{"type":"element","tag":"code","props":{"className":[]},"children":[{"type":"text","value":"@nuxtjs/composition-api/module"}]},{"type":"text","value":" from your buildModules"}]},{"type":"element","tag":"p","props":{},"children":[{"type":"text","value":"You don't have to immediately update your imports yet - Nuxt Bridge will automatically provide a 'shim' for most imports you currently have, to give you time to migrate to the new, Nuxt 3-compatible composables, with the following exceptions:"}]},{"type":"element","tag":"ul","props":{},"children":[{"type":"element","tag":"li","props":{},"children":[{"type":"element","tag":"code","props":{"className":[]},"children":[{"type":"text","value":"withContext"}]},{"type":"text","value":" has been removed. See "},{"type":"element","tag":"a","props":{"href":"/docs/bridge/nuxt3-compatible-api#usecontext-and-withcontext"},"children":[{"type":"text","value":"below"}]},{"type":"text","value":"."}]},{"type":"element","tag":"li","props":{},"children":[{"type":"element","tag":"code","props":{"className":[]},"children":[{"type":"text","value":"useStatic"}]},{"type":"text","value":" has been removed. There is no current replacement. Feel free to raise a discussion if you have a use case for this."}]},{"type":"element","tag":"li","props":{},"children":[{"type":"element","tag":"code","props":{"className":[]},"children":[{"type":"text","value":"reqRef"}]},{"type":"text","value":" and "},{"type":"element","tag":"code","props":{"className":[]},"children":[{"type":"text","value":"reqSsrRef"}]},{"type":"text","value":", which were deprecated, have now been removed entirely. Follow the instructions below regarding "},{"type":"element","tag":"a","props":{"href":"/docs/bridge/nuxt3-compatible-api#ssrref-and-shallowssrref"},"children":[{"type":"text","value":"ssrRef"}]},{"type":"text","value":" to replace this."}]}]},{"type":"element","tag":"h3","props":{"id":"set-bridgecapi"},"children":[{"type":"text","value":"Set "},{"type":"element","tag":"code","props":{"className":[]},"children":[{"type":"text","value":"bridge.capi"}]}]},{"type":"element","tag":"pre","props":{"className":"language-ts shiki shiki-themes material-theme-lighter material-theme-lighter material-theme-palenight","code":"import { defineNuxtConfig } from '@nuxt/bridge'\n\nexport default defineNuxtConfig({\n  bridge: {\n    capi: true,\n    nitro: false // If migration to Nitro is complete, set to true\n  }\n})\n","language":"ts","meta":"","style":""},"children":[{"type":"element","tag":"code","props":{"__ignoreMap":""},"children":[{"type":"element","tag":"span","props":{"class":"line","line":1},"children":[{"type":"element","tag":"span","props":{"style":"--shiki-light:#39ADB5;--shiki-default:#39ADB5;--shiki-dark:#89DDFF;--shiki-light-font-style:italic;--shiki-default-font-style:italic;--shiki-dark-font-style:italic"},"children":[{"type":"text","value":"import"}]},{"type":"element","tag":"span","props":{"style":"--shiki-light:#39ADB5;--shiki-default:#39ADB5;--shiki-dark:#89DDFF"},"children":[{"type":"text","value":" {"}]},{"type":"element","tag":"span","props":{"style":"--shiki-light:#90A4AE;--shiki-default:#90A4AE;--shiki-dark:#BABED8"},"children":[{"type":"text","value":" defineNuxtConfig"}]},{"type":"element","tag":"span","props":{"style":"--shiki-light:#39ADB5;--shiki-default:#39ADB5;--shiki-dark:#89DDFF"},"children":[{"type":"text","value":" }"}]},{"type":"element","tag":"span","props":{"style":"--shiki-light:#39ADB5;--shiki-default:#39ADB5;--shiki-dark:#89DDFF;--shiki-light-font-style:italic;--shiki-default-font-style:italic;--shiki-dark-font-style:italic"},"children":[{"type":"text","value":" from"}]},{"type":"element","tag":"span","props":{"style":"--shiki-light:#39ADB5;--shiki-default:#39ADB5;--shiki-dark:#89DDFF"},"children":[{"type":"text","value":" '"}]},{"type":"element","tag":"span","props":{"style":"--shiki-light:#91B859;--shiki-default:#91B859;--shiki-dark:#C3E88D"},"children":[{"type":"text","value":"@nuxt/bridge"}]},{"type":"element","tag":"span","props":{"style":"--shiki-light:#39ADB5;--shiki-default:#39ADB5;--shiki-dark:#89DDFF"},"children":[{"type":"text","value":"'\n"}]}]},{"type":"element","tag":"span","props":{"class":"line","line":2},"children":[{"type":"element","tag":"span","props":{"emptyLinePlaceholder":true},"children":[{"type":"text","value":"\n"}]}]},{"type":"element","tag":"span","props":{"class":"line","line":3},"children":[{"type":"element","tag":"span","props":{"style":"--shiki-light:#39ADB5;--shiki-default:#39ADB5;--shiki-dark:#89DDFF;--shiki-light-font-style:italic;--shiki-default-font-style:italic;--shiki-dark-font-style:italic"},"children":[{"type":"text","value":"export"}]},{"type":"element","tag":"span","props":{"style":"--shiki-light:#39ADB5;--shiki-default:#39ADB5;--shiki-dark:#89DDFF;--shiki-light-font-style:italic;--shiki-default-font-style:italic;--shiki-dark-font-style:italic"},"children":[{"type":"text","value":" default"}]},{"type":"element","tag":"span","props":{"style":"--shiki-light:#6182B8;--shiki-default:#6182B8;--shiki-dark:#82AAFF"},"children":[{"type":"text","value":" defineNuxtConfig"}]},{"type":"element","tag":"span","props":{"style":"--shiki-light:#90A4AE;--shiki-default:#90A4AE;--shiki-dark:#BABED8"},"children":[{"type":"text","value":"("}]},{"type":"element","tag":"span","props":{"style":"--shiki-light:#39ADB5;--shiki-default:#39ADB5;--shiki-dark:#89DDFF"},"children":[{"type":"text","value":"{\n"}]}]},{"type":"element","tag":"span","props":{"class":"line","line":4},"children":[{"type":"element","tag":"span","props":{"style":"--shiki-light:#E53935;--shiki-default:#E53935;--shiki-dark:#F07178"},"children":[{"type":"text","value":"  bridge"}]},{"type":"element","tag":"span","props":{"style":"--shiki-light:#39ADB5;--shiki-default:#39ADB5;--shiki-dark:#89DDFF"},"children":[{"type":"text","value":":"}]},{"type":"element","tag":"span","props":{"style":"--shiki-light:#39ADB5;--shiki-default:#39ADB5;--shiki-dark:#89DDFF"},"children":[{"type":"text","value":" {\n"}]}]},{"type":"element","tag":"span","props":{"class":"line","line":5},"children":[{"type":"element","tag":"span","props":{"style":"--shiki-light:#E53935;--shiki-default:#E53935;--shiki-dark:#F07178"},"children":[{"type":"text","value":"    capi"}]},{"type":"element","tag":"span","props":{"style":"--shiki-light:#39ADB5;--shiki-default:#39ADB5;--shiki-dark:#89DDFF"},"children":[{"type":"text","value":":"}]},{"type":"element","tag":"span","props":{"style":"--shiki-light:#FF5370;--shiki-default:#FF5370;--shiki-dark:#FF9CAC"},"children":[{"type":"text","value":" true"}]},{"type":"element","tag":"span","props":{"style":"--shiki-light:#39ADB5;--shiki-default:#39ADB5;--shiki-dark:#89DDFF"},"children":[{"type":"text","value":",\n"}]}]},{"type":"element","tag":"span","props":{"class":"line","line":6},"children":[{"type":"element","tag":"span","props":{"style":"--shiki-light:#E53935;--shiki-default:#E53935;--shiki-dark:#F07178"},"children":[{"type":"text","value":"    nitro"}]},{"type":"element","tag":"span","props":{"style":"--shiki-light:#39ADB5;--shiki-default:#39ADB5;--shiki-dark:#89DDFF"},"children":[{"type":"text","value":":"}]},{"type":"element","tag":"span","props":{"style":"--shiki-light:#FF5370;--shiki-default:#FF5370;--shiki-dark:#FF9CAC"},"children":[{"type":"text","value":" false"}]},{"type":"element","tag":"span","props":{"style":"--shiki-light:#90A4AE;--shiki-default:#90A4AE;--shiki-dark:#676E95;--shiki-light-font-style:italic;--shiki-default-font-style:italic;--shiki-dark-font-style:italic"},"children":[{"type":"text","value":" // If migration to Nitro is complete, set to true\n"}]}]},{"type":"element","tag":"span","props":{"class":"line","line":7},"children":[{"type":"element","tag":"span","props":{"style":"--shiki-light:#39ADB5;--shiki-default:#39ADB5;--shiki-dark:#89DDFF"},"children":[{"type":"text","value":"  }\n"}]}]},{"type":"element","tag":"span","props":{"class":"line","line":8},"children":[{"type":"element","tag":"span","props":{"style":"--shiki-light:#39ADB5;--shiki-default:#39ADB5;--shiki-dark:#89DDFF"},"children":[{"type":"text","value":"}"}]},{"type":"element","tag":"span","props":{"style":"--shiki-light:#90A4AE;--shiki-default:#90A4AE;--shiki-dark:#BABED8"},"children":[{"type":"text","value":")\n"}]}]}]}]},{"type":"element","tag":"p","props":{},"children":[{"type":"text","value":"For each other composable you are using from "},{"type":"element","tag":"code","props":{"className":[]},"children":[{"type":"text","value":"@nuxtjs/composition-api"}]},{"type":"text","value":", follow the steps below."}]},{"type":"element","tag":"h3","props":{"id":"usefetch"},"children":[{"type":"text","value":"useFetch"}]},{"type":"element","tag":"p","props":{},"children":[{"type":"element","tag":"code","props":{"className":[]},"children":[{"type":"text","value":"$fetchState"}]},{"type":"text","value":" and "},{"type":"element","tag":"code","props":{"className":[]},"children":[{"type":"text","value":"$fetch"}]},{"type":"text","value":" have been removed."}]},{"type":"element","tag":"pre","props":{"className":"language-diff shiki shiki-themes material-theme-lighter material-theme-lighter material-theme-palenight","code":"const {\n- $fetch,\n- $fetchState,\n+ fetch,\n+ fetchState,\n} = useFetch(() => { posts.value = await $fetch('/api/posts') })\n","language":"diff","meta":"","style":""},"children":[{"type":"element","tag":"code","props":{"__ignoreMap":""},"children":[{"type":"element","tag":"span","props":{"class":"line","line":1},"children":[{"type":"element","tag":"span","props":{"style":"--shiki-light:#90A4AE;--shiki-default:#90A4AE;--shiki-dark:#BABED8"},"children":[{"type":"text","value":"const {\n"}]}]},{"type":"element","tag":"span","props":{"class":"line","line":2},"children":[{"type":"element","tag":"span","props":{"style":"--shiki-light:#39ADB5;--shiki-default:#39ADB5;--shiki-dark:#89DDFF"},"children":[{"type":"text","value":"-"}]},{"type":"element","tag":"span","props":{"style":"--shiki-light:#E53935;--shiki-default:#E53935;--shiki-dark:#F07178"},"children":[{"type":"text","value":" $fetch,\n"}]}]},{"type":"element","tag":"span","props":{"class":"line","line":3},"children":[{"type":"element","tag":"span","props":{"style":"--shiki-light:#39ADB5;--shiki-default:#39ADB5;--shiki-dark:#89DDFF"},"children":[{"type":"text","value":"-"}]},{"type":"element","tag":"span","props":{"style":"--shiki-light:#E53935;--shiki-default:#E53935;--shiki-dark:#F07178"},"children":[{"type":"text","value":" $fetchState,\n"}]}]},{"type":"element","tag":"span","props":{"class":"line","line":4},"children":[{"type":"element","tag":"span","props":{"style":"--shiki-light:#39ADB5;--shiki-default:#39ADB5;--shiki-dark:#89DDFF"},"children":[{"type":"text","value":"+"}]},{"type":"element","tag":"span","props":{"style":"--shiki-light:#91B859;--shiki-default:#91B859;--shiki-dark:#C3E88D"},"children":[{"type":"text","value":" fetch,\n"}]}]},{"type":"element","tag":"span","props":{"class":"line","line":5},"children":[{"type":"element","tag":"span","props":{"style":"--shiki-light:#39ADB5;--shiki-default:#39ADB5;--shiki-dark:#89DDFF"},"children":[{"type":"text","value":"+"}]},{"type":"element","tag":"span","props":{"style":"--shiki-light:#91B859;--shiki-default:#91B859;--shiki-dark:#C3E88D"},"children":[{"type":"text","value":" fetchState,\n"}]}]},{"type":"element","tag":"span","props":{"class":"line","line":6},"children":[{"type":"element","tag":"span","props":{"style":"--shiki-light:#90A4AE;--shiki-default:#90A4AE;--shiki-dark:#BABED8"},"children":[{"type":"text","value":"} = useFetch(() => { posts.value = await $fetch('/api/posts') })\n"}]}]}]}]},{"type":"element","tag":"h3","props":{"id":"definenuxtmiddleware"},"children":[{"type":"element","tag":"code","props":{"className":[]},"children":[{"type":"text","value":"defineNuxtMiddleware"}]}]},{"type":"element","tag":"p","props":{},"children":[{"type":"text","value":"This was a type-helper stub function that is now removed."}]},{"type":"element","tag":"p","props":{},"children":[{"type":"text","value":"Remove the "},{"type":"element","tag":"code","props":{"className":[]},"children":[{"type":"text","value":"defineNuxtMiddleware"}]},{"type":"text","value":" wrapper:"}]},{"type":"element","tag":"pre","props":{"className":"language-diff shiki shiki-themes material-theme-lighter material-theme-lighter material-theme-palenight","code":"- import { defineNuxtMiddleware } from '@nuxtjs/composition-api`\n- export default defineNuxtMiddleware((ctx) => {})\n+ export default (ctx) => {}\n","language":"diff","meta":"","style":""},"children":[{"type":"element","tag":"code","props":{"__ignoreMap":""},"children":[{"type":"element","tag":"span","props":{"class":"line","line":1},"children":[{"type":"element","tag":"span","props":{"style":"--shiki-light:#39ADB5;--shiki-default:#39ADB5;--shiki-dark:#89DDFF"},"children":[{"type":"text","value":"-"}]},{"type":"element","tag":"span","props":{"style":"--shiki-light:#E53935;--shiki-default:#E53935;--shiki-dark:#F07178"},"children":[{"type":"text","value":" import { defineNuxtMiddleware } from '@nuxtjs/composition-api`\n"}]}]},{"type":"element","tag":"span","props":{"class":"line","line":2},"children":[{"type":"element","tag":"span","props":{"style":"--shiki-light:#39ADB5;--shiki-default:#39ADB5;--shiki-dark:#89DDFF"},"children":[{"type":"text","value":"-"}]},{"type":"element","tag":"span","props":{"style":"--shiki-light:#E53935;--shiki-default:#E53935;--shiki-dark:#F07178"},"children":[{"type":"text","value":" export default defineNuxtMiddleware((ctx) => {})\n"}]}]},{"type":"element","tag":"span","props":{"class":"line","line":3},"children":[{"type":"element","tag":"span","props":{"style":"--shiki-light:#39ADB5;--shiki-default:#39ADB5;--shiki-dark:#89DDFF"},"children":[{"type":"text","value":"+"}]},{"type":"element","tag":"span","props":{"style":"--shiki-light:#91B859;--shiki-default:#91B859;--shiki-dark:#C3E88D"},"children":[{"type":"text","value":" export default (ctx) => {}\n"}]}]}]}]},{"type":"element","tag":"p","props":{},"children":[{"type":"text","value":"For typescript support, you can use "},{"type":"element","tag":"code","props":{"className":[]},"children":[{"type":"text","value":"@nuxt/types"}]},{"type":"text","value":":"}]},{"type":"element","tag":"pre","props":{"className":"language-ts shiki shiki-themes material-theme-lighter material-theme-lighter material-theme-palenight","code":"import type { Middleware } from '@nuxt/types'\n\nexport default <Middleware> function (ctx) { }\n","language":"ts","meta":"","style":""},"children":[{"type":"element","tag":"code","props":{"__ignoreMap":""},"children":[{"type":"element","tag":"span","props":{"class":"line","line":1},"children":[{"type":"element","tag":"span","props":{"style":"--shiki-light:#39ADB5;--shiki-default:#39ADB5;--shiki-dark:#89DDFF;--shiki-light-font-style:italic;--shiki-default-font-style:italic;--shiki-dark-font-style:italic"},"children":[{"type":"text","value":"import"}]},{"type":"element","tag":"span","props":{"style":"--shiki-light:#39ADB5;--shiki-default:#39ADB5;--shiki-dark:#89DDFF;--shiki-light-font-style:italic;--shiki-default-font-style:italic;--shiki-dark-font-style:italic"},"children":[{"type":"text","value":" type"}]},{"type":"element","tag":"span","props":{"style":"--shiki-light:#39ADB5;--shiki-default:#39ADB5;--shiki-dark:#89DDFF"},"children":[{"type":"text","value":" {"}]},{"type":"element","tag":"span","props":{"style":"--shiki-light:#90A4AE;--shiki-default:#90A4AE;--shiki-dark:#BABED8"},"children":[{"type":"text","value":" Middleware"}]},{"type":"element","tag":"span","props":{"style":"--shiki-light:#39ADB5;--shiki-default:#39ADB5;--shiki-dark:#89DDFF"},"children":[{"type":"text","value":" }"}]},{"type":"element","tag":"span","props":{"style":"--shiki-light:#39ADB5;--shiki-default:#39ADB5;--shiki-dark:#89DDFF;--shiki-light-font-style:italic;--shiki-default-font-style:italic;--shiki-dark-font-style:italic"},"children":[{"type":"text","value":" from"}]},{"type":"element","tag":"span","props":{"style":"--shiki-light:#39ADB5;--shiki-default:#39ADB5;--shiki-dark:#89DDFF"},"children":[{"type":"text","value":" '"}]},{"type":"element","tag":"span","props":{"style":"--shiki-light:#91B859;--shiki-default:#91B859;--shiki-dark:#C3E88D"},"children":[{"type":"text","value":"@nuxt/types"}]},{"type":"element","tag":"span","props":{"style":"--shiki-light:#39ADB5;--shiki-default:#39ADB5;--shiki-dark:#89DDFF"},"children":[{"type":"text","value":"'\n"}]}]},{"type":"element","tag":"span","props":{"class":"line","line":2},"children":[{"type":"element","tag":"span","props":{"emptyLinePlaceholder":true},"children":[{"type":"text","value":"\n"}]}]},{"type":"element","tag":"span","props":{"class":"line","line":3},"children":[{"type":"element","tag":"span","props":{"style":"--shiki-light:#39ADB5;--shiki-default:#39ADB5;--shiki-dark:#89DDFF;--shiki-light-font-style:italic;--shiki-default-font-style:italic;--shiki-dark-font-style:italic"},"children":[{"type":"text","value":"export"}]},{"type":"element","tag":"span","props":{"style":"--shiki-light:#39ADB5;--shiki-default:#39ADB5;--shiki-dark:#89DDFF;--shiki-light-font-style:italic;--shiki-default-font-style:italic;--shiki-dark-font-style:italic"},"children":[{"type":"text","value":" default"}]},{"type":"element","tag":"span","props":{"style":"--shiki-light:#90A4AE;--shiki-default:#90A4AE;--shiki-dark:#BABED8"},"children":[{"type":"text","value":" <"}]},{"type":"element","tag":"span","props":{"style":"--shiki-light:#E2931D;--shiki-default:#E2931D;--shiki-dark:#FFCB6B"},"children":[{"type":"text","value":"Middleware"}]},{"type":"element","tag":"span","props":{"style":"--shiki-light:#90A4AE;--shiki-default:#90A4AE;--shiki-dark:#BABED8"},"children":[{"type":"text","value":"> "}]},{"type":"element","tag":"span","props":{"style":"--shiki-light:#9C3EDA;--shiki-default:#9C3EDA;--shiki-dark:#C792EA"},"children":[{"type":"text","value":"function"}]},{"type":"element","tag":"span","props":{"style":"--shiki-light:#39ADB5;--shiki-default:#39ADB5;--shiki-dark:#89DDFF"},"children":[{"type":"text","value":" ("}]},{"type":"element","tag":"span","props":{"style":"--shiki-light:#90A4AE;--shiki-default:#90A4AE;--shiki-dark:#BABED8;--shiki-light-font-style:italic;--shiki-default-font-style:italic;--shiki-dark-font-style:italic"},"children":[{"type":"text","value":"ctx"}]},{"type":"element","tag":"span","props":{"style":"--shiki-light:#39ADB5;--shiki-default:#39ADB5;--shiki-dark:#89DDFF"},"children":[{"type":"text","value":")"}]},{"type":"element","tag":"span","props":{"style":"--shiki-light:#39ADB5;--shiki-default:#39ADB5;--shiki-dark:#89DDFF"},"children":[{"type":"text","value":" {"}]},{"type":"element","tag":"span","props":{"style":"--shiki-light:#39ADB5;--shiki-default:#39ADB5;--shiki-dark:#89DDFF"},"children":[{"type":"text","value":" }\n"}]}]}]}]},{"type":"element","tag":"h3","props":{"id":"definenuxtplugin"},"children":[{"type":"element","tag":"code","props":{"className":[]},"children":[{"type":"text","value":"defineNuxtPlugin"}]}]},{"type":"element","tag":"p","props":{},"children":[{"type":"text","value":"This was a type-helper stub function that is now removed."}]},{"type":"element","tag":"p","props":{},"children":[{"type":"text","value":"You may also keep using Nuxt 2-style plugins, by removing the function (as with "},{"type":"element","tag":"a","props":{"href":"#definenuxtmiddleware"},"children":[{"type":"text","value":"defineNuxtMiddleware"}]},{"type":"text","value":")."}]},{"type":"element","tag":"p","props":{},"children":[{"type":"text","value":"Remove the "},{"type":"element","tag":"code","props":{"className":[]},"children":[{"type":"text","value":"defineNuxtPlugin"}]},{"type":"text","value":" wrapper:"}]},{"type":"element","tag":"pre","props":{"className":"language-diff shiki shiki-themes material-theme-lighter material-theme-lighter material-theme-palenight","code":"- import { defineNuxtPlugin } from '@nuxtjs/composition-api'\n- export default defineNuxtPlugin((ctx, inject) => {})\n+ export default (ctx, inject) => {}\n","language":"diff","meta":"","style":""},"children":[{"type":"element","tag":"code","props":{"__ignoreMap":""},"children":[{"type":"element","tag":"span","props":{"class":"line","line":1},"children":[{"type":"element","tag":"span","props":{"style":"--shiki-light:#39ADB5;--shiki-default:#39ADB5;--shiki-dark:#89DDFF"},"children":[{"type":"text","value":"-"}]},{"type":"element","tag":"span","props":{"style":"--shiki-light:#E53935;--shiki-default:#E53935;--shiki-dark:#F07178"},"children":[{"type":"text","value":" import { defineNuxtPlugin } from '@nuxtjs/composition-api'\n"}]}]},{"type":"element","tag":"span","props":{"class":"line","line":2},"children":[{"type":"element","tag":"span","props":{"style":"--shiki-light:#39ADB5;--shiki-default:#39ADB5;--shiki-dark:#89DDFF"},"children":[{"type":"text","value":"-"}]},{"type":"element","tag":"span","props":{"style":"--shiki-light:#E53935;--shiki-default:#E53935;--shiki-dark:#F07178"},"children":[{"type":"text","value":" export default defineNuxtPlugin((ctx, inject) => {})\n"}]}]},{"type":"element","tag":"span","props":{"class":"line","line":3},"children":[{"type":"element","tag":"span","props":{"style":"--shiki-light:#39ADB5;--shiki-default:#39ADB5;--shiki-dark:#89DDFF"},"children":[{"type":"text","value":"+"}]},{"type":"element","tag":"span","props":{"style":"--shiki-light:#91B859;--shiki-default:#91B859;--shiki-dark:#C3E88D"},"children":[{"type":"text","value":" export default (ctx, inject) => {}\n"}]}]}]}]},{"type":"element","tag":"p","props":{},"children":[{"type":"text","value":"For typescript support, you can use "},{"type":"element","tag":"code","props":{"className":[]},"children":[{"type":"text","value":"@nuxt/types"}]},{"type":"text","value":":"}]},{"type":"element","tag":"pre","props":{"className":"language-ts shiki shiki-themes material-theme-lighter material-theme-lighter material-theme-palenight","code":"import type { Plugin } from '@nuxt/types'\n\nexport default <Plugin> function (ctx, inject) {}\n","language":"ts","meta":"","style":""},"children":[{"type":"element","tag":"code","props":{"__ignoreMap":""},"children":[{"type":"element","tag":"span","props":{"class":"line","line":1},"children":[{"type":"element","tag":"span","props":{"style":"--shiki-light:#39ADB5;--shiki-default:#39ADB5;--shiki-dark:#89DDFF;--shiki-light-font-style:italic;--shiki-default-font-style:italic;--shiki-dark-font-style:italic"},"children":[{"type":"text","value":"import"}]},{"type":"element","tag":"span","props":{"style":"--shiki-light:#39ADB5;--shiki-default:#39ADB5;--shiki-dark:#89DDFF;--shiki-light-font-style:italic;--shiki-default-font-style:italic;--shiki-dark-font-style:italic"},"children":[{"type":"text","value":" type"}]},{"type":"element","tag":"span","props":{"style":"--shiki-light:#39ADB5;--shiki-default:#39ADB5;--shiki-dark:#89DDFF"},"children":[{"type":"text","value":" {"}]},{"type":"element","tag":"span","props":{"style":"--shiki-light:#90A4AE;--shiki-default:#90A4AE;--shiki-dark:#BABED8"},"children":[{"type":"text","value":" Plugin"}]},{"type":"element","tag":"span","props":{"style":"--shiki-light:#39ADB5;--shiki-default:#39ADB5;--shiki-dark:#89DDFF"},"children":[{"type":"text","value":" }"}]},{"type":"element","tag":"span","props":{"style":"--shiki-light:#39ADB5;--shiki-default:#39ADB5;--shiki-dark:#89DDFF;--shiki-light-font-style:italic;--shiki-default-font-style:italic;--shiki-dark-font-style:italic"},"children":[{"type":"text","value":" from"}]},{"type":"element","tag":"span","props":{"style":"--shiki-light:#39ADB5;--shiki-default:#39ADB5;--shiki-dark:#89DDFF"},"children":[{"type":"text","value":" '"}]},{"type":"element","tag":"span","props":{"style":"--shiki-light:#91B859;--shiki-default:#91B859;--shiki-dark:#C3E88D"},"children":[{"type":"text","value":"@nuxt/types"}]},{"type":"element","tag":"span","props":{"style":"--shiki-light:#39ADB5;--shiki-default:#39ADB5;--shiki-dark:#89DDFF"},"children":[{"type":"text","value":"'\n"}]}]},{"type":"element","tag":"span","props":{"class":"line","line":2},"children":[{"type":"element","tag":"span","props":{"emptyLinePlaceholder":true},"children":[{"type":"text","value":"\n"}]}]},{"type":"element","tag":"span","props":{"class":"line","line":3},"children":[{"type":"element","tag":"span","props":{"style":"--shiki-light:#39ADB5;--shiki-default:#39ADB5;--shiki-dark:#89DDFF;--shiki-light-font-style:italic;--shiki-default-font-style:italic;--shiki-dark-font-style:italic"},"children":[{"type":"text","value":"export"}]},{"type":"element","tag":"span","props":{"style":"--shiki-light:#39ADB5;--shiki-default:#39ADB5;--shiki-dark:#89DDFF;--shiki-light-font-style:italic;--shiki-default-font-style:italic;--shiki-dark-font-style:italic"},"children":[{"type":"text","value":" default"}]},{"type":"element","tag":"span","props":{"style":"--shiki-light:#90A4AE;--shiki-default:#90A4AE;--shiki-dark:#BABED8"},"children":[{"type":"text","value":" <"}]},{"type":"element","tag":"span","props":{"style":"--shiki-light:#E2931D;--shiki-default:#E2931D;--shiki-dark:#FFCB6B"},"children":[{"type":"text","value":"Plugin"}]},{"type":"element","tag":"span","props":{"style":"--shiki-light:#90A4AE;--shiki-default:#90A4AE;--shiki-dark:#BABED8"},"children":[{"type":"text","value":"> "}]},{"type":"element","tag":"span","props":{"style":"--shiki-light:#9C3EDA;--shiki-default:#9C3EDA;--shiki-dark:#C792EA"},"children":[{"type":"text","value":"function"}]},{"type":"element","tag":"span","props":{"style":"--shiki-light:#39ADB5;--shiki-default:#39ADB5;--shiki-dark:#89DDFF"},"children":[{"type":"text","value":" ("}]},{"type":"element","tag":"span","props":{"style":"--shiki-light:#90A4AE;--shiki-default:#90A4AE;--shiki-dark:#BABED8;--shiki-light-font-style:italic;--shiki-default-font-style:italic;--shiki-dark-font-style:italic"},"children":[{"type":"text","value":"ctx"}]},{"type":"element","tag":"span","props":{"style":"--shiki-light:#39ADB5;--shiki-default:#39ADB5;--shiki-dark:#89DDFF"},"children":[{"type":"text","value":","}]},{"type":"element","tag":"span","props":{"style":"--shiki-light:#90A4AE;--shiki-default:#90A4AE;--shiki-dark:#BABED8;--shiki-light-font-style:italic;--shiki-default-font-style:italic;--shiki-dark-font-style:italic"},"children":[{"type":"text","value":" inject"}]},{"type":"element","tag":"span","props":{"style":"--shiki-light:#39ADB5;--shiki-default:#39ADB5;--shiki-dark:#89DDFF"},"children":[{"type":"text","value":")"}]},{"type":"element","tag":"span","props":{"style":"--shiki-light:#39ADB5;--shiki-default:#39ADB5;--shiki-dark:#89DDFF"},"children":[{"type":"text","value":" {}\n"}]}]}]}]},{"type":"element","tag":"alert","props":{"type":"warning"},"children":[{"type":"element","tag":"p","props":{},"children":[{"type":"text","value":"While this example is valid, Nuxt 3 introduces a new defineNuxtPlugin function that has a slightly different signature."}]}]},{"type":"element","tag":"read-more","props":{"link":"/docs/guide/directory-structure/plugins#creating-plugins"},"children":[]},{"type":"element","tag":"h3","props":{"id":"userouter-and-useroute"},"children":[{"type":"element","tag":"code","props":{"className":[]},"children":[{"type":"text","value":"useRouter"}]},{"type":"text","value":" and "},{"type":"element","tag":"code","props":{"className":[]},"children":[{"type":"text","value":"useRoute"}]}]},{"type":"element","tag":"p","props":{},"children":[{"type":"text","value":"Nuxt Bridge provides direct replacements for these composables via "},{"type":"element","tag":"a","props":{"href":"/docs/api/composables/use-router"},"children":[{"type":"element","tag":"code","props":{"className":[]},"children":[{"type":"text","value":"useRouter"}]}]},{"type":"text","value":"  and "},{"type":"element","tag":"code","props":{"className":[]},"children":[{"type":"text","value":"useRoute"}]},{"type":"text","value":"."}]},{"type":"element","tag":"p","props":{},"children":[{"type":"text","value":"The only key difference is that "},{"type":"element","tag":"a","props":{"href":"/docs/api/composables/use-route"},"children":[{"type":"element","tag":"code","props":{"className":[]},"children":[{"type":"text","value":"useRoute"}]}]},{"type":"text","value":" no longer returns a computed property."}]},{"type":"element","tag":"pre","props":{"className":"language-diff shiki shiki-themes material-theme-lighter material-theme-lighter material-theme-palenight","code":"- import { useRouter, useRoute } from '@nuxtjs/composition-api'\n\n  const router = useRouter()\n  const route = useRoute()\n\n- console.log(route.value.path)\n+ console.log(route.path)\n","language":"diff","meta":"","style":""},"children":[{"type":"element","tag":"code","props":{"__ignoreMap":""},"children":[{"type":"element","tag":"span","props":{"class":"line","line":1},"children":[{"type":"element","tag":"span","props":{"style":"--shiki-light:#39ADB5;--shiki-default:#39ADB5;--shiki-dark:#89DDFF"},"children":[{"type":"text","value":"-"}]},{"type":"element","tag":"span","props":{"style":"--shiki-light:#E53935;--shiki-default:#E53935;--shiki-dark:#F07178"},"children":[{"type":"text","value":" import { useRouter, useRoute } from '@nuxtjs/composition-api'\n"}]}]},{"type":"element","tag":"span","props":{"class":"line","line":2},"children":[{"type":"element","tag":"span","props":{"emptyLinePlaceholder":true},"children":[{"type":"text","value":"\n"}]}]},{"type":"element","tag":"span","props":{"class":"line","line":3},"children":[{"type":"element","tag":"span","props":{"style":"--shiki-light:#90A4AE;--shiki-default:#90A4AE;--shiki-dark:#BABED8"},"children":[{"type":"text","value":"  const router = useRouter()\n"}]}]},{"type":"element","tag":"span","props":{"class":"line","line":4},"children":[{"type":"element","tag":"span","props":{"style":"--shiki-light:#90A4AE;--shiki-default:#90A4AE;--shiki-dark:#BABED8"},"children":[{"type":"text","value":"  const route = useRoute()\n"}]}]},{"type":"element","tag":"span","props":{"class":"line","line":5},"children":[{"type":"element","tag":"span","props":{"emptyLinePlaceholder":true},"children":[{"type":"text","value":"\n"}]}]},{"type":"element","tag":"span","props":{"class":"line","line":6},"children":[{"type":"element","tag":"span","props":{"style":"--shiki-light:#39ADB5;--shiki-default:#39ADB5;--shiki-dark:#89DDFF"},"children":[{"type":"text","value":"-"}]},{"type":"element","tag":"span","props":{"style":"--shiki-light:#E53935;--shiki-default:#E53935;--shiki-dark:#F07178"},"children":[{"type":"text","value":" console.log(route.value.path)\n"}]}]},{"type":"element","tag":"span","props":{"class":"line","line":7},"children":[{"type":"element","tag":"span","props":{"style":"--shiki-light:#39ADB5;--shiki-default:#39ADB5;--shiki-dark:#89DDFF"},"children":[{"type":"text","value":"+"}]},{"type":"element","tag":"span","props":{"style":"--shiki-light:#91B859;--shiki-default:#91B859;--shiki-dark:#C3E88D"},"children":[{"type":"text","value":" console.log(route.path)\n"}]}]}]}]},{"type":"element","tag":"style","props":{},"children":[{"type":"text","value":"html .light .shiki span {color: var(--shiki-light);background: var(--shiki-light-bg);font-style: var(--shiki-light-font-style);font-weight: var(--shiki-light-font-weight);text-decoration: var(--shiki-light-text-decoration);}html.light .shiki span {color: var(--shiki-light);background: var(--shiki-light-bg);font-style: var(--shiki-light-font-style);font-weight: var(--shiki-light-font-weight);text-decoration: var(--shiki-light-text-decoration);}html .default .shiki span {color: var(--shiki-default);background: var(--shiki-default-bg);font-style: var(--shiki-default-font-style);font-weight: var(--shiki-default-font-weight);text-decoration: var(--shiki-default-text-decoration);}html .shiki span {color: var(--shiki-default);background: var(--shiki-default-bg);font-style: var(--shiki-default-font-style);font-weight: var(--shiki-default-font-weight);text-decoration: var(--shiki-default-text-decoration);}html .dark .shiki span {color: var(--shiki-dark);background: var(--shiki-dark-bg);font-style: var(--shiki-dark-font-style);font-weight: var(--shiki-dark-font-weight);text-decoration: var(--shiki-dark-text-decoration);}html.dark .shiki span {color: var(--shiki-dark);background: var(--shiki-dark-bg);font-style: var(--shiki-dark-font-style);font-weight: var(--shiki-dark-font-weight);text-decoration: var(--shiki-dark-text-decoration);}"}]}],"toc":{"title":"","searchDepth":2,"depth":2,"links":[{"id":"remove-modules","depth":2,"text":"Remove Modules"},{"id":"using-vuecomposition-api","depth":2,"text":"Using @vue/composition-api"},{"id":"migrating-from-nuxtjscomposition-api","depth":2,"text":"Migrating from @nuxtjs/composition-api","children":[{"id":"remove-nuxtjscomposition-apimodule-from-your-buildmodules","depth":3,"text":"Remove @nuxtjs/composition-api/module from your buildModules"},{"id":"set-bridgecapi","depth":3,"text":"Set bridge.capi"},{"id":"usefetch","depth":3,"text":"useFetch"},{"id":"definenuxtmiddleware","depth":3,"text":"defineNuxtMiddleware"},{"id":"definenuxtplugin","depth":3,"text":"defineNuxtPlugin"},{"id":"userouter-and-useroute","depth":3,"text":"useRouter and useRoute"}]}]}},"_type":"markdown","_id":"nuxt-docs:1.docs:6.bridge:3.bridge-composition-api.md","_source":"nuxt-docs","_file":"1.docs/6.bridge/3.bridge-composition-api.md","_extension":"md"}