{"_path":"/docs/api/components/nuxt-loading-indicator","_dir":"components","_draft":false,"_partial":false,"_locale":"","title":"<NuxtLoadingIndicator>","description":"Display a progress bar between page navigations.","links":[{"label":"Source","icon":"i-simple-icons-github","to":"https://github.com/nuxt/nuxt/blob/main/packages/nuxt/src/app/components/nuxt-loading-indicator.ts","size":"xs"}],"body":{"type":"root","children":[{"type":"element","tag":"h2","props":{"id":"usage"},"children":[{"type":"text","value":"Usage"}]},{"type":"element","tag":"p","props":{},"children":[{"type":"text","value":"Add "},{"type":"element","tag":"code","props":{"className":[]},"children":[{"type":"text","value":"<NuxtLoadingIndicator/>"}]},{"type":"text","value":" in your "},{"type":"element","tag":"a","props":{"href":"/docs/guide/directory-structure/app"},"children":[{"type":"element","tag":"code","props":{"className":[]},"children":[{"type":"text","value":"app.vue"}]}]},{"type":"text","value":" or "},{"type":"element","tag":"a","props":{"href":"/docs/guide/directory-structure/layouts"},"children":[{"type":"element","tag":"code","props":{"className":[]},"children":[{"type":"text","value":"layouts/"}]}]},{"type":"text","value":"."}]},{"type":"element","tag":"pre","props":{"className":"language-vue shiki shiki-themes material-theme-lighter material-theme-lighter material-theme-palenight","code":"<template>\n  <NuxtLoadingIndicator />\n  <NuxtLayout>\n    <NuxtPage />\n  </NuxtLayout>\n</template>\n","filename":"app.vue","language":"vue","meta":"","style":""},"children":[{"type":"element","tag":"code","props":{"__ignoreMap":""},"children":[{"type":"element","tag":"span","props":{"class":"line","line":1},"children":[{"type":"element","tag":"span","props":{"style":"--shiki-light:#39ADB5;--shiki-default:#39ADB5;--shiki-dark:#89DDFF"},"children":[{"type":"text","value":"<"}]},{"type":"element","tag":"span","props":{"style":"--shiki-light:#E53935;--shiki-default:#E53935;--shiki-dark:#F07178"},"children":[{"type":"text","value":"template"}]},{"type":"element","tag":"span","props":{"style":"--shiki-light:#39ADB5;--shiki-default:#39ADB5;--shiki-dark:#89DDFF"},"children":[{"type":"text","value":">\n"}]}]},{"type":"element","tag":"span","props":{"class":"line","line":2},"children":[{"type":"element","tag":"span","props":{"style":"--shiki-light:#39ADB5;--shiki-default:#39ADB5;--shiki-dark:#89DDFF"},"children":[{"type":"text","value":"  <"}]},{"type":"element","tag":"span","props":{"style":"--shiki-light:#E53935;--shiki-default:#E53935;--shiki-dark:#F07178"},"children":[{"type":"text","value":"NuxtLoadingIndicator"}]},{"type":"element","tag":"span","props":{"style":"--shiki-light:#39ADB5;--shiki-default:#39ADB5;--shiki-dark:#89DDFF"},"children":[{"type":"text","value":" />\n"}]}]},{"type":"element","tag":"span","props":{"class":"line","line":3},"children":[{"type":"element","tag":"span","props":{"style":"--shiki-light:#39ADB5;--shiki-default:#39ADB5;--shiki-dark:#89DDFF"},"children":[{"type":"text","value":"  <"}]},{"type":"element","tag":"span","props":{"style":"--shiki-light:#E53935;--shiki-default:#E53935;--shiki-dark:#F07178"},"children":[{"type":"text","value":"NuxtLayout"}]},{"type":"element","tag":"span","props":{"style":"--shiki-light:#39ADB5;--shiki-default:#39ADB5;--shiki-dark:#89DDFF"},"children":[{"type":"text","value":">\n"}]}]},{"type":"element","tag":"span","props":{"class":"line","line":4},"children":[{"type":"element","tag":"span","props":{"style":"--shiki-light:#39ADB5;--shiki-default:#39ADB5;--shiki-dark:#89DDFF"},"children":[{"type":"text","value":"    <"}]},{"type":"element","tag":"span","props":{"style":"--shiki-light:#E53935;--shiki-default:#E53935;--shiki-dark:#F07178"},"children":[{"type":"text","value":"NuxtPage"}]},{"type":"element","tag":"span","props":{"style":"--shiki-light:#39ADB5;--shiki-default:#39ADB5;--shiki-dark:#89DDFF"},"children":[{"type":"text","value":" />\n"}]}]},{"type":"element","tag":"span","props":{"class":"line","line":5},"children":[{"type":"element","tag":"span","props":{"style":"--shiki-light:#39ADB5;--shiki-default:#39ADB5;--shiki-dark:#89DDFF"},"children":[{"type":"text","value":"  </"}]},{"type":"element","tag":"span","props":{"style":"--shiki-light:#E53935;--shiki-default:#E53935;--shiki-dark:#F07178"},"children":[{"type":"text","value":"NuxtLayout"}]},{"type":"element","tag":"span","props":{"style":"--shiki-light:#39ADB5;--shiki-default:#39ADB5;--shiki-dark:#89DDFF"},"children":[{"type":"text","value":">\n"}]}]},{"type":"element","tag":"span","props":{"class":"line","line":6},"children":[{"type":"element","tag":"span","props":{"style":"--shiki-light:#39ADB5;--shiki-default:#39ADB5;--shiki-dark:#89DDFF"},"children":[{"type":"text","value":"</"}]},{"type":"element","tag":"span","props":{"style":"--shiki-light:#E53935;--shiki-default:#E53935;--shiki-dark:#F07178"},"children":[{"type":"text","value":"template"}]},{"type":"element","tag":"span","props":{"style":"--shiki-light:#39ADB5;--shiki-default:#39ADB5;--shiki-dark:#89DDFF"},"children":[{"type":"text","value":">\n"}]}]}]}]},{"type":"element","tag":"link-example","props":{"to":"/docs/examples/routing/pages"},"children":[]},{"type":"element","tag":"h2","props":{"id":"slots"},"children":[{"type":"text","value":"Slots"}]},{"type":"element","tag":"p","props":{},"children":[{"type":"text","value":"You can pass custom HTML or components through the loading indicator's default slot."}]},{"type":"element","tag":"h2","props":{"id":"props"},"children":[{"type":"text","value":"Props"}]},{"type":"element","tag":"ul","props":{},"children":[{"type":"element","tag":"li","props":{},"children":[{"type":"element","tag":"code","props":{"className":[]},"children":[{"type":"text","value":"color"}]},{"type":"text","value":": The color of the loading bar. It can be set to "},{"type":"element","tag":"code","props":{"className":[]},"children":[{"type":"text","value":"false"}]},{"type":"text","value":" to turn off explicit color styling."}]},{"type":"element","tag":"li","props":{},"children":[{"type":"element","tag":"code","props":{"className":[]},"children":[{"type":"text","value":"errorColor"}]},{"type":"text","value":": The color of the loading bar when "},{"type":"element","tag":"code","props":{"className":[]},"children":[{"type":"text","value":"error"}]},{"type":"text","value":" is set to "},{"type":"element","tag":"code","props":{"className":[]},"children":[{"type":"text","value":"true"}]},{"type":"text","value":"."}]},{"type":"element","tag":"li","props":{},"children":[{"type":"element","tag":"code","props":{"className":[]},"children":[{"type":"text","value":"height"}]},{"type":"text","value":": Height of the loading bar, in pixels (default "},{"type":"element","tag":"code","props":{"className":[]},"children":[{"type":"text","value":"3"}]},{"type":"text","value":")."}]},{"type":"element","tag":"li","props":{},"children":[{"type":"element","tag":"code","props":{"className":[]},"children":[{"type":"text","value":"duration"}]},{"type":"text","value":": Duration of the loading bar, in milliseconds (default "},{"type":"element","tag":"code","props":{"className":[]},"children":[{"type":"text","value":"2000"}]},{"type":"text","value":")."}]},{"type":"element","tag":"li","props":{},"children":[{"type":"element","tag":"code","props":{"className":[]},"children":[{"type":"text","value":"throttle"}]},{"type":"text","value":": Throttle the appearing and hiding, in milliseconds (default "},{"type":"element","tag":"code","props":{"className":[]},"children":[{"type":"text","value":"200"}]},{"type":"text","value":")."}]},{"type":"element","tag":"li","props":{},"children":[{"type":"element","tag":"code","props":{"className":[]},"children":[{"type":"text","value":"estimatedProgress"}]},{"type":"text","value":": By default Nuxt will back off as it approaches 100%. You can provide a custom function to customize the progress estimation, which is a function that receives the duration of the loading bar (above) and the elapsed time. It should return a value between 0 and 100."}]}]},{"type":"element","tag":"note","props":{},"children":[{"type":"element","tag":"p","props":{},"children":[{"type":"text","value":"This component is optional. "},{"type":"element","tag":"br","props":{},"children":[]},{"type":"text","value":"\nTo achieve full customization, you can implement your own one based on "},{"type":"element","tag":"a","props":{"href":"https://github.com/nuxt/nuxt/blob/main/packages/nuxt/src/app/components/nuxt-loading-indicator.ts","rel":["nofollow"]},"children":[{"type":"text","value":"its source code"}]},{"type":"text","value":"."}]}]},{"type":"element","tag":"note","props":{},"children":[{"type":"element","tag":"p","props":{},"children":[{"type":"text","value":"You can hook into the underlying indicator instance using "},{"type":"element","tag":"a","props":{"href":"/docs/api/composables/use-loading-indicator"},"children":[{"type":"text","value":"the "},{"type":"element","tag":"code","props":{"className":[]},"children":[{"type":"text","value":"useLoadingIndicator"}]},{"type":"text","value":" composable"}]},{"type":"text","value":", which will allow you to trigger start/finish events yourself."}]}]},{"type":"element","tag":"tip","props":{},"children":[{"type":"element","tag":"p","props":{},"children":[{"type":"text","value":"The loading indicator's speed gradually decreases after reaching a specific point controlled by "},{"type":"element","tag":"code","props":{"className":[]},"children":[{"type":"text","value":"estimatedProgress"}]},{"type":"text","value":". This adjustment provides a more accurate reflection of longer page loading times and prevents the indicator from prematurely showing 100% completion."}]}]},{"type":"element","tag":"style","props":{},"children":[{"type":"text","value":"html .light .shiki span {color: var(--shiki-light);background: var(--shiki-light-bg);font-style: var(--shiki-light-font-style);font-weight: var(--shiki-light-font-weight);text-decoration: var(--shiki-light-text-decoration);}html.light .shiki span {color: var(--shiki-light);background: var(--shiki-light-bg);font-style: var(--shiki-light-font-style);font-weight: var(--shiki-light-font-weight);text-decoration: var(--shiki-light-text-decoration);}html .default .shiki span {color: var(--shiki-default);background: var(--shiki-default-bg);font-style: var(--shiki-default-font-style);font-weight: var(--shiki-default-font-weight);text-decoration: var(--shiki-default-text-decoration);}html .shiki span {color: var(--shiki-default);background: var(--shiki-default-bg);font-style: var(--shiki-default-font-style);font-weight: var(--shiki-default-font-weight);text-decoration: var(--shiki-default-text-decoration);}html .dark .shiki span {color: var(--shiki-dark);background: var(--shiki-dark-bg);font-style: var(--shiki-dark-font-style);font-weight: var(--shiki-dark-font-weight);text-decoration: var(--shiki-dark-text-decoration);}html.dark .shiki span {color: var(--shiki-dark);background: var(--shiki-dark-bg);font-style: var(--shiki-dark-font-style);font-weight: var(--shiki-dark-font-weight);text-decoration: var(--shiki-dark-text-decoration);}"}]}],"toc":{"title":"","searchDepth":2,"depth":2,"links":[{"id":"usage","depth":2,"text":"Usage"},{"id":"slots","depth":2,"text":"Slots"},{"id":"props","depth":2,"text":"Props"}]}},"_type":"markdown","_id":"nuxt-docs:1.docs:3.api:1.components:5.nuxt-loading-indicator.md","_source":"nuxt-docs","_file":"1.docs/3.api/1.components/5.nuxt-loading-indicator.md","_extension":"md"}