[null,{"_path":"/deploy/nuxthub","_dir":"deploy","_draft":false,"_partial":false,"_locale":"","title":"NuxtHub","description":"Deploy your full-stack Nuxt application globally on your Cloudflare account.","componentImg":"NuxtHub","logoSrc":"/assets/integrations/nuxthub.svg","category":"Hosting","featured":true,"nitroPreset":"cloudflare-pages","website":"https://hub.nuxt.com/?utm_source=nuxt-website&utm_medium=deploy-page","_type":"markdown","_id":"content:3.deploy:nuxthub.md","_source":"content","_file":"3.deploy/nuxthub.md","_extension":"md"}]