{"_path":"/deploy","_dir":{"_path":"/deploy/_dir","navigation":false,"title":"Dir"},"_draft":false,"_partial":false,"_locale":"","navigation":{"title":"Deploy","icon":"i-ph-rocket-launch-duotone"},"title":"Deploy a Nuxt App","description":"Discover the different ways to deploy your Nuxt project on different hosting providers.","links":[{"label":"Deployment Guide","icon":"i-ph-cloud-duotone","to":"/docs/getting-started/deployment","color":"black","size":"md"}],"_id":"content:3.deploy.yml","_type":"yaml","_source":"content","_file":"3.deploy.yml","_extension":"yml"}