{"_path":"/deploy/aws-amplify","_dir":"deploy","_draft":false,"_partial":false,"_locale":"","title":"AWS Amplify","description":"Deploy your Nuxt Application to AWS Amplify infrastructure.","componentImg":"Amplify","logoIcon":"i-logos-aws-amplify","category":"Hosting","nitroPreset":"aws-amplify","website":"https://aws.amazon.com/amplify/?trk=bed847b4-6e9f-4e09-ba09-0d4680a0447b&sc_channel=el","body":{"type":"root","children":[{"type":"element","tag":"tip","props":{},"children":[{"type":"element","tag":"p","props":{},"children":[{"type":"element","tag":"strong","props":{},"children":[{"type":"text","value":"Zero Configuration ✨"}]}]},{"type":"element","tag":"br","props":{},"children":[]},{"type":"element","tag":"p","props":{},"children":[{"type":"text","value":"Integration with AWS Amplify is possible with zero configuration, "},{"type":"element","tag":"a","props":{"href":"https://nitro.unjs.io/deploy#zero-config-providers","rel":["nofollow"]},"children":[{"type":"text","value":"learn more"}]},{"type":"text","value":"."}]}]},{"type":"element","tag":"h2","props":{"id":"setup"},"children":[{"type":"text","value":"Setup"}]},{"type":"element","tag":"ol","props":{},"children":[{"type":"element","tag":"li","props":{},"children":[{"type":"text","value":"Login to the "},{"type":"element","tag":"a","props":{"href":"https://console.aws.amazon.com/amplify/?trk=01c5a476-5997-4e6a-88b9-fd0a0a5bbe34&sc_channel=el","rel":["nofollow"]},"children":[{"type":"text","value":"AWS Amplify Hosting Console"}]}]},{"type":"element","tag":"li","props":{},"children":[{"type":"text","value":"Click on \"Get Started\" > Amplify Hosting (Host your web app)"}]},{"type":"element","tag":"li","props":{},"children":[{"type":"text","value":"Select and authorize access to your Git repository provider and select the main branch"}]},{"type":"element","tag":"li","props":{},"children":[{"type":"text","value":"Choose a name for your app, make sure build settings are auto-detected and optionally set requirement environment variables under the advanced section"}]},{"type":"element","tag":"li","props":{},"children":[{"type":"text","value":"Optionally, select Enable SSR logging to enable server-side logging to your Amazon CloudWatch account"}]},{"type":"element","tag":"li","props":{},"children":[{"type":"text","value":"Confirm configuration and click on \"Save and Deploy\""}]}]},{"type":"element","tag":"h2","props":{"id":"learn-more"},"children":[{"type":"text","value":"Learn more"}]},{"type":"element","tag":"read-more","props":{"target":"_blank","to":"https://www.youtube.com/watch?v=CAk5_XGkOG4"},"children":[{"type":"element","tag":"p","props":{},"children":[{"type":"text","value":"Watch an Amplify Hosting tutorial with Nuxt"}]}]},{"type":"element","tag":"read-more","props":{"target":"_blank","to":"https://nitro.unjs.io/deploy/providers/aws-amplify"},"children":[{"type":"element","tag":"p","props":{},"children":[{"type":"text","value":"Head over "},{"type":"element","tag":"strong","props":{},"children":[{"type":"text","value":"Nitro documentation"}]},{"type":"text","value":" to learn more about the aws-amplify deployment preset."}]}]}],"toc":{"title":"","searchDepth":2,"depth":2,"links":[{"id":"setup","depth":2,"text":"Setup"},{"id":"learn-more","depth":2,"text":"Learn more"}]}},"_type":"markdown","_id":"content:3.deploy:aws-amplify.md","_source":"content","_file":"3.deploy/aws-amplify.md","_extension":"md"}