[{"_path":"/docs/api/utils/add-route-middleware","_dir":"utils","_draft":false,"_partial":false,"_locale":"","title":"addRouteMiddleware","description":"addRouteMiddleware() is a helper function to dynamically add middleware in your application.","links":[{"label":"Source","icon":"i-simple-icons-github","to":"https://github.com/nuxt/nuxt/blob/main/packages/nuxt/src/app/composables/router.ts","size":"xs"}],"_type":"markdown","_id":"nuxt-docs:1.docs:3.api:3.utils:add-route-middleware.md","_source":"nuxt-docs","_file":"1.docs/3.api/3.utils/add-route-middleware.md","_extension":"md"},{"_path":"/docs/api/utils/clear-error","_dir":"utils","_draft":false,"_partial":false,"_locale":"","title":"clearError","description":"The clearError composable clears all handled errors.","links":[{"label":"Source","icon":"i-simple-icons-github","to":"https://github.com/nuxt/nuxt/blob/main/packages/nuxt/src/app/composables/error.ts","size":"xs"}],"_type":"markdown","_id":"nuxt-docs:1.docs:3.api:3.utils:clear-error.md","_source":"nuxt-docs","_file":"1.docs/3.api/3.utils/clear-error.md","_extension":"md"}]