{"_path":"/docs/guide/recipes/vite-plugin","_dir":"recipes","_draft":false,"_partial":false,"_locale":"","title":"Using Vite Plugins in Nuxt","description":"Learn how to integrate Vite plugins into your Nuxt project.","navigation":{"title":"Vite Plugins"},"body":{"type":"root","children":[{"type":"element","tag":"p","props":{},"children":[{"type":"text","value":"While Nuxt modules offer extensive functionality, sometimes a specific Vite plugin might meet your needs more directly."}]},{"type":"element","tag":"p","props":{},"children":[{"type":"text","value":"First, we need to install the Vite plugin, for our example, we'll use "},{"type":"element","tag":"code","props":{"className":[]},"children":[{"type":"text","value":"@rollup/plugin-yaml"}]},{"type":"text","value":":"}]},{"type":"element","tag":"code-group","props":{},"children":[{"type":"element","tag":"pre","props":{"className":"language-bash shiki shiki-themes material-theme-lighter material-theme-lighter material-theme-palenight","code":"npm install @rollup/plugin-yaml\n","filename":"npm","language":"bash","meta":"","style":""},"children":[{"type":"element","tag":"code","props":{"__ignoreMap":""},"children":[{"type":"element","tag":"span","props":{"class":"line","line":1},"children":[{"type":"element","tag":"span","props":{"style":"--shiki-light:#E2931D;--shiki-default:#E2931D;--shiki-dark:#FFCB6B"},"children":[{"type":"text","value":"npm"}]},{"type":"element","tag":"span","props":{"style":"--shiki-light:#91B859;--shiki-default:#91B859;--shiki-dark:#C3E88D"},"children":[{"type":"text","value":" install"}]},{"type":"element","tag":"span","props":{"style":"--shiki-light:#91B859;--shiki-default:#91B859;--shiki-dark:#C3E88D"},"children":[{"type":"text","value":" @rollup/plugin-yaml\n"}]}]}]}]},{"type":"element","tag":"pre","props":{"className":"language-bash shiki shiki-themes material-theme-lighter material-theme-lighter material-theme-palenight","code":"yarn add @rollup/plugin-yaml\n","filename":"yarn","language":"bash","meta":"","style":""},"children":[{"type":"element","tag":"code","props":{"__ignoreMap":""},"children":[{"type":"element","tag":"span","props":{"class":"line","line":1},"children":[{"type":"element","tag":"span","props":{"style":"--shiki-light:#E2931D;--shiki-default:#E2931D;--shiki-dark:#FFCB6B"},"children":[{"type":"text","value":"yarn"}]},{"type":"element","tag":"span","props":{"style":"--shiki-light:#91B859;--shiki-default:#91B859;--shiki-dark:#C3E88D"},"children":[{"type":"text","value":" add"}]},{"type":"element","tag":"span","props":{"style":"--shiki-light:#91B859;--shiki-default:#91B859;--shiki-dark:#C3E88D"},"children":[{"type":"text","value":" @rollup/plugin-yaml\n"}]}]}]}]},{"type":"element","tag":"pre","props":{"className":"language-bash shiki shiki-themes material-theme-lighter material-theme-lighter material-theme-palenight","code":"pnpm add @rollup/plugin-yaml\n","filename":"pnpm","language":"bash","meta":"","style":""},"children":[{"type":"element","tag":"code","props":{"__ignoreMap":""},"children":[{"type":"element","tag":"span","props":{"class":"line","line":1},"children":[{"type":"element","tag":"span","props":{"style":"--shiki-light:#E2931D;--shiki-default:#E2931D;--shiki-dark:#FFCB6B"},"children":[{"type":"text","value":"pnpm"}]},{"type":"element","tag":"span","props":{"style":"--shiki-light:#91B859;--shiki-default:#91B859;--shiki-dark:#C3E88D"},"children":[{"type":"text","value":" add"}]},{"type":"element","tag":"span","props":{"style":"--shiki-light:#91B859;--shiki-default:#91B859;--shiki-dark:#C3E88D"},"children":[{"type":"text","value":" @rollup/plugin-yaml\n"}]}]}]}]},{"type":"element","tag":"pre","props":{"className":"language-bash shiki shiki-themes material-theme-lighter material-theme-lighter material-theme-palenight","code":"bun add @rollup/plugin-yaml\n","filename":"bun","language":"bash","meta":"","style":""},"children":[{"type":"element","tag":"code","props":{"__ignoreMap":""},"children":[{"type":"element","tag":"span","props":{"class":"line","line":1},"children":[{"type":"element","tag":"span","props":{"style":"--shiki-light:#E2931D;--shiki-default:#E2931D;--shiki-dark:#FFCB6B"},"children":[{"type":"text","value":"bun"}]},{"type":"element","tag":"span","props":{"style":"--shiki-light:#91B859;--shiki-default:#91B859;--shiki-dark:#C3E88D"},"children":[{"type":"text","value":" add"}]},{"type":"element","tag":"span","props":{"style":"--shiki-light:#91B859;--shiki-default:#91B859;--shiki-dark:#C3E88D"},"children":[{"type":"text","value":" @rollup/plugin-yaml\n"}]}]}]}]}]},{"type":"element","tag":"p","props":{},"children":[{"type":"text","value":"Next, we need to import and add it to our "},{"type":"element","tag":"a","props":{"href":"/docs/guide/directory-structure/nuxt-config"},"children":[{"type":"element","tag":"code","props":{"className":[]},"children":[{"type":"text","value":"nuxt.config.ts"}]}]},{"type":"text","value":" file:"}]},{"type":"element","tag":"pre","props":{"className":"language-ts shiki shiki-themes material-theme-lighter material-theme-lighter material-theme-palenight","code":"import yaml from '@rollup/plugin-yaml'\n\nexport default defineNuxtConfig({\n  vite: {\n    plugins: [\n      yaml()\n    ]\n  }\n})\n","filename":"nuxt.config.ts","language":"ts","meta":"","style":""},"children":[{"type":"element","tag":"code","props":{"__ignoreMap":""},"children":[{"type":"element","tag":"span","props":{"class":"line","line":1},"children":[{"type":"element","tag":"span","props":{"style":"--shiki-light:#39ADB5;--shiki-default:#39ADB5;--shiki-dark:#89DDFF;--shiki-light-font-style:italic;--shiki-default-font-style:italic;--shiki-dark-font-style:italic"},"children":[{"type":"text","value":"import"}]},{"type":"element","tag":"span","props":{"style":"--shiki-light:#90A4AE;--shiki-default:#90A4AE;--shiki-dark:#BABED8"},"children":[{"type":"text","value":" yaml "}]},{"type":"element","tag":"span","props":{"style":"--shiki-light:#39ADB5;--shiki-default:#39ADB5;--shiki-dark:#89DDFF;--shiki-light-font-style:italic;--shiki-default-font-style:italic;--shiki-dark-font-style:italic"},"children":[{"type":"text","value":"from"}]},{"type":"element","tag":"span","props":{"style":"--shiki-light:#39ADB5;--shiki-default:#39ADB5;--shiki-dark:#89DDFF"},"children":[{"type":"text","value":" '"}]},{"type":"element","tag":"span","props":{"style":"--shiki-light:#91B859;--shiki-default:#91B859;--shiki-dark:#C3E88D"},"children":[{"type":"text","value":"@rollup/plugin-yaml"}]},{"type":"element","tag":"span","props":{"style":"--shiki-light:#39ADB5;--shiki-default:#39ADB5;--shiki-dark:#89DDFF"},"children":[{"type":"text","value":"'\n"}]}]},{"type":"element","tag":"span","props":{"class":"line","line":2},"children":[{"type":"element","tag":"span","props":{"emptyLinePlaceholder":true},"children":[{"type":"text","value":"\n"}]}]},{"type":"element","tag":"span","props":{"class":"line","line":3},"children":[{"type":"element","tag":"span","props":{"style":"--shiki-light:#39ADB5;--shiki-default:#39ADB5;--shiki-dark:#89DDFF;--shiki-light-font-style:italic;--shiki-default-font-style:italic;--shiki-dark-font-style:italic"},"children":[{"type":"text","value":"export"}]},{"type":"element","tag":"span","props":{"style":"--shiki-light:#39ADB5;--shiki-default:#39ADB5;--shiki-dark:#89DDFF;--shiki-light-font-style:italic;--shiki-default-font-style:italic;--shiki-dark-font-style:italic"},"children":[{"type":"text","value":" default"}]},{"type":"element","tag":"span","props":{"style":"--shiki-light:#6182B8;--shiki-default:#6182B8;--shiki-dark:#82AAFF"},"children":[{"type":"text","value":" defineNuxtConfig"}]},{"type":"element","tag":"span","props":{"style":"--shiki-light:#90A4AE;--shiki-default:#90A4AE;--shiki-dark:#BABED8"},"children":[{"type":"text","value":"("}]},{"type":"element","tag":"span","props":{"style":"--shiki-light:#39ADB5;--shiki-default:#39ADB5;--shiki-dark:#89DDFF"},"children":[{"type":"text","value":"{\n"}]}]},{"type":"element","tag":"span","props":{"class":"line","line":4},"children":[{"type":"element","tag":"span","props":{"style":"--shiki-light:#E53935;--shiki-default:#E53935;--shiki-dark:#F07178"},"children":[{"type":"text","value":"  vite"}]},{"type":"element","tag":"span","props":{"style":"--shiki-light:#39ADB5;--shiki-default:#39ADB5;--shiki-dark:#89DDFF"},"children":[{"type":"text","value":":"}]},{"type":"element","tag":"span","props":{"style":"--shiki-light:#39ADB5;--shiki-default:#39ADB5;--shiki-dark:#89DDFF"},"children":[{"type":"text","value":" {\n"}]}]},{"type":"element","tag":"span","props":{"class":"line","line":5},"children":[{"type":"element","tag":"span","props":{"style":"--shiki-light:#E53935;--shiki-default:#E53935;--shiki-dark:#F07178"},"children":[{"type":"text","value":"    plugins"}]},{"type":"element","tag":"span","props":{"style":"--shiki-light:#39ADB5;--shiki-default:#39ADB5;--shiki-dark:#89DDFF"},"children":[{"type":"text","value":":"}]},{"type":"element","tag":"span","props":{"style":"--shiki-light:#90A4AE;--shiki-default:#90A4AE;--shiki-dark:#BABED8"},"children":[{"type":"text","value":" [\n"}]}]},{"type":"element","tag":"span","props":{"class":"line","line":6},"children":[{"type":"element","tag":"span","props":{"style":"--shiki-light:#6182B8;--shiki-default:#6182B8;--shiki-dark:#82AAFF"},"children":[{"type":"text","value":"      yaml"}]},{"type":"element","tag":"span","props":{"style":"--shiki-light:#90A4AE;--shiki-default:#90A4AE;--shiki-dark:#BABED8"},"children":[{"type":"text","value":"()\n"}]}]},{"type":"element","tag":"span","props":{"class":"line","line":7},"children":[{"type":"element","tag":"span","props":{"style":"--shiki-light:#90A4AE;--shiki-default:#90A4AE;--shiki-dark:#BABED8"},"children":[{"type":"text","value":"    ]\n"}]}]},{"type":"element","tag":"span","props":{"class":"line","line":8},"children":[{"type":"element","tag":"span","props":{"style":"--shiki-light:#39ADB5;--shiki-default:#39ADB5;--shiki-dark:#89DDFF"},"children":[{"type":"text","value":"  }\n"}]}]},{"type":"element","tag":"span","props":{"class":"line","line":9},"children":[{"type":"element","tag":"span","props":{"style":"--shiki-light:#39ADB5;--shiki-default:#39ADB5;--shiki-dark:#89DDFF"},"children":[{"type":"text","value":"}"}]},{"type":"element","tag":"span","props":{"style":"--shiki-light:#90A4AE;--shiki-default:#90A4AE;--shiki-dark:#BABED8"},"children":[{"type":"text","value":")\n"}]}]}]}]},{"type":"element","tag":"p","props":{},"children":[{"type":"text","value":"Now we installed and configured our Vite plugin, we can start using YAML files directly in our project."}]},{"type":"element","tag":"p","props":{},"children":[{"type":"text","value":"For example, we can have a "},{"type":"element","tag":"code","props":{"className":[]},"children":[{"type":"text","value":"config.yaml"}]},{"type":"text","value":" that stores configuration data and import this data in our Nuxt components:"}]},{"type":"element","tag":"code-group","props":{},"children":[{"type":"element","tag":"pre","props":{"className":"language-yaml shiki shiki-themes material-theme-lighter material-theme-lighter material-theme-palenight","code":"greeting: \"Hello, Nuxt with Vite!\"\n","filename":"data/hello.yaml","language":"yaml","meta":"","style":""},"children":[{"type":"element","tag":"code","props":{"__ignoreMap":""},"children":[{"type":"element","tag":"span","props":{"class":"line","line":1},"children":[{"type":"element","tag":"span","props":{"style":"--shiki-light:#E53935;--shiki-default:#E53935;--shiki-dark:#F07178"},"children":[{"type":"text","value":"greeting"}]},{"type":"element","tag":"span","props":{"style":"--shiki-light:#39ADB5;--shiki-default:#39ADB5;--shiki-dark:#89DDFF"},"children":[{"type":"text","value":":"}]},{"type":"element","tag":"span","props":{"style":"--shiki-light:#39ADB5;--shiki-default:#39ADB5;--shiki-dark:#89DDFF"},"children":[{"type":"text","value":" \""}]},{"type":"element","tag":"span","props":{"style":"--shiki-light:#91B859;--shiki-default:#91B859;--shiki-dark:#C3E88D"},"children":[{"type":"text","value":"Hello, Nuxt with Vite!"}]},{"type":"element","tag":"span","props":{"style":"--shiki-light:#39ADB5;--shiki-default:#39ADB5;--shiki-dark:#89DDFF"},"children":[{"type":"text","value":"\"\n"}]}]}]}]},{"type":"element","tag":"pre","props":{"className":"language-vue shiki shiki-themes material-theme-lighter material-theme-lighter material-theme-palenight","code":"<script setup>\nimport config from '~/data/hello.yaml'\n</script>\n\n<template>\n  <h1>{{ config.greeting }}</h1>\n</template>\n","filename":"components/Hello.vue","language":"vue","meta":"","style":""},"children":[{"type":"element","tag":"code","props":{"__ignoreMap":""},"children":[{"type":"element","tag":"span","props":{"class":"line","line":1},"children":[{"type":"element","tag":"span","props":{"style":"--shiki-light:#39ADB5;--shiki-default:#39ADB5;--shiki-dark:#89DDFF"},"children":[{"type":"text","value":"<"}]},{"type":"element","tag":"span","props":{"style":"--shiki-light:#E53935;--shiki-default:#E53935;--shiki-dark:#F07178"},"children":[{"type":"text","value":"script"}]},{"type":"element","tag":"span","props":{"style":"--shiki-light:#9C3EDA;--shiki-default:#9C3EDA;--shiki-dark:#C792EA"},"children":[{"type":"text","value":" setup"}]},{"type":"element","tag":"span","props":{"style":"--shiki-light:#39ADB5;--shiki-default:#39ADB5;--shiki-dark:#89DDFF"},"children":[{"type":"text","value":">\n"}]}]},{"type":"element","tag":"span","props":{"class":"line","line":2},"children":[{"type":"element","tag":"span","props":{"style":"--shiki-light:#39ADB5;--shiki-default:#39ADB5;--shiki-dark:#89DDFF;--shiki-light-font-style:italic;--shiki-default-font-style:italic;--shiki-dark-font-style:italic"},"children":[{"type":"text","value":"import"}]},{"type":"element","tag":"span","props":{"style":"--shiki-light:#90A4AE;--shiki-default:#90A4AE;--shiki-dark:#BABED8"},"children":[{"type":"text","value":" config "}]},{"type":"element","tag":"span","props":{"style":"--shiki-light:#39ADB5;--shiki-default:#39ADB5;--shiki-dark:#89DDFF;--shiki-light-font-style:italic;--shiki-default-font-style:italic;--shiki-dark-font-style:italic"},"children":[{"type":"text","value":"from"}]},{"type":"element","tag":"span","props":{"style":"--shiki-light:#39ADB5;--shiki-default:#39ADB5;--shiki-dark:#89DDFF"},"children":[{"type":"text","value":" '"}]},{"type":"element","tag":"span","props":{"style":"--shiki-light:#91B859;--shiki-default:#91B859;--shiki-dark:#C3E88D"},"children":[{"type":"text","value":"~/data/hello.yaml"}]},{"type":"element","tag":"span","props":{"style":"--shiki-light:#39ADB5;--shiki-default:#39ADB5;--shiki-dark:#89DDFF"},"children":[{"type":"text","value":"'\n"}]}]},{"type":"element","tag":"span","props":{"class":"line","line":3},"children":[{"type":"element","tag":"span","props":{"style":"--shiki-light:#39ADB5;--shiki-default:#39ADB5;--shiki-dark:#89DDFF"},"children":[{"type":"text","value":"</"}]},{"type":"element","tag":"span","props":{"style":"--shiki-light:#E53935;--shiki-default:#E53935;--shiki-dark:#F07178"},"children":[{"type":"text","value":"script"}]},{"type":"element","tag":"span","props":{"style":"--shiki-light:#39ADB5;--shiki-default:#39ADB5;--shiki-dark:#89DDFF"},"children":[{"type":"text","value":">\n"}]}]},{"type":"element","tag":"span","props":{"class":"line","line":4},"children":[{"type":"element","tag":"span","props":{"emptyLinePlaceholder":true},"children":[{"type":"text","value":"\n"}]}]},{"type":"element","tag":"span","props":{"class":"line","line":5},"children":[{"type":"element","tag":"span","props":{"style":"--shiki-light:#39ADB5;--shiki-default:#39ADB5;--shiki-dark:#89DDFF"},"children":[{"type":"text","value":"<"}]},{"type":"element","tag":"span","props":{"style":"--shiki-light:#E53935;--shiki-default:#E53935;--shiki-dark:#F07178"},"children":[{"type":"text","value":"template"}]},{"type":"element","tag":"span","props":{"style":"--shiki-light:#39ADB5;--shiki-default:#39ADB5;--shiki-dark:#89DDFF"},"children":[{"type":"text","value":">\n"}]}]},{"type":"element","tag":"span","props":{"class":"line","line":6},"children":[{"type":"element","tag":"span","props":{"style":"--shiki-light:#39ADB5;--shiki-default:#39ADB5;--shiki-dark:#89DDFF"},"children":[{"type":"text","value":"  <"}]},{"type":"element","tag":"span","props":{"style":"--shiki-light:#E53935;--shiki-default:#E53935;--shiki-dark:#F07178"},"children":[{"type":"text","value":"h1"}]},{"type":"element","tag":"span","props":{"style":"--shiki-light:#39ADB5;--shiki-default:#39ADB5;--shiki-dark:#89DDFF"},"children":[{"type":"text","value":">{{"}]},{"type":"element","tag":"span","props":{"style":"--shiki-light:#90A4AE;--shiki-default:#90A4AE;--shiki-dark:#BABED8"},"children":[{"type":"text","value":" config"}]},{"type":"element","tag":"span","props":{"style":"--shiki-light:#39ADB5;--shiki-default:#39ADB5;--shiki-dark:#89DDFF"},"children":[{"type":"text","value":"."}]},{"type":"element","tag":"span","props":{"style":"--shiki-light:#90A4AE;--shiki-default:#90A4AE;--shiki-dark:#BABED8"},"children":[{"type":"text","value":"greeting "}]},{"type":"element","tag":"span","props":{"style":"--shiki-light:#39ADB5;--shiki-default:#39ADB5;--shiki-dark:#89DDFF"},"children":[{"type":"text","value":"}}</"}]},{"type":"element","tag":"span","props":{"style":"--shiki-light:#E53935;--shiki-default:#E53935;--shiki-dark:#F07178"},"children":[{"type":"text","value":"h1"}]},{"type":"element","tag":"span","props":{"style":"--shiki-light:#39ADB5;--shiki-default:#39ADB5;--shiki-dark:#89DDFF"},"children":[{"type":"text","value":">\n"}]}]},{"type":"element","tag":"span","props":{"class":"line","line":7},"children":[{"type":"element","tag":"span","props":{"style":"--shiki-light:#39ADB5;--shiki-default:#39ADB5;--shiki-dark:#89DDFF"},"children":[{"type":"text","value":"</"}]},{"type":"element","tag":"span","props":{"style":"--shiki-light:#E53935;--shiki-default:#E53935;--shiki-dark:#F07178"},"children":[{"type":"text","value":"template"}]},{"type":"element","tag":"span","props":{"style":"--shiki-light:#39ADB5;--shiki-default:#39ADB5;--shiki-dark:#89DDFF"},"children":[{"type":"text","value":">\n"}]}]}]}]}]},{"type":"element","tag":"style","props":{},"children":[{"type":"text","value":"html .light .shiki span {color: var(--shiki-light);background: var(--shiki-light-bg);font-style: var(--shiki-light-font-style);font-weight: var(--shiki-light-font-weight);text-decoration: var(--shiki-light-text-decoration);}html.light .shiki span {color: var(--shiki-light);background: var(--shiki-light-bg);font-style: var(--shiki-light-font-style);font-weight: var(--shiki-light-font-weight);text-decoration: var(--shiki-light-text-decoration);}html .default .shiki span {color: var(--shiki-default);background: var(--shiki-default-bg);font-style: var(--shiki-default-font-style);font-weight: var(--shiki-default-font-weight);text-decoration: var(--shiki-default-text-decoration);}html .shiki span {color: var(--shiki-default);background: var(--shiki-default-bg);font-style: var(--shiki-default-font-style);font-weight: var(--shiki-default-font-weight);text-decoration: var(--shiki-default-text-decoration);}html .dark .shiki span {color: var(--shiki-dark);background: var(--shiki-dark-bg);font-style: var(--shiki-dark-font-style);font-weight: var(--shiki-dark-font-weight);text-decoration: var(--shiki-dark-text-decoration);}html.dark .shiki span {color: var(--shiki-dark);background: var(--shiki-dark-bg);font-style: var(--shiki-dark-font-style);font-weight: var(--shiki-dark-font-weight);text-decoration: var(--shiki-dark-text-decoration);}"}]}],"toc":{"title":"","searchDepth":2,"depth":2,"links":[]}},"_type":"markdown","_id":"nuxt-docs:1.docs:2.guide:4.recipes:2.vite-plugin.md","_source":"nuxt-docs","_file":"1.docs/2.guide/4.recipes/2.vite-plugin.md","_extension":"md"}